{
  "description": "### 8.28 afwtdn\n\nReduce broadband noise from input samples using Wavelets.\n\nA description of the accepted options follows.\n\n**sigma**\n\n    Set the noise sigma, allowed range is from 0 to 1. Default value is 0. This option controls strength of denoising applied to input samples. Most useful way to set this option is via decibels, eg. -45dB. \n\n**levels**\n\n    Set the number of wavelet levels of decomposition. Allowed range is from 1 to 12. Default value is 10. Setting this too low make denoising performance very poor. \n\n**wavet**\n\n    Set wavelet type for decomposition of input frame. They are sorted by number of coefficients, from lowest to highest. More coefficients means worse filtering speed, but overall better quality. Available wavelets are: \u2018sym2\u2019 \u2018sym4\u2019 \u2018rbior68\u2019 \u2018deb10\u2019 \u2018sym10\u2019 \u2018coif5\u2019 \u2018bl3\u2019 \n\n**percent**\n\n    Set percent of full denoising. Allowed range is from 0 to 100 percent. Default value is 85 percent or partial denoising. \n\n**profile**\n\n    If enabled, first input frame will be used as noise profile. If first frame samples contain non-noise performance will be very poor. \n\n**adaptive**\n\n    If enabled, input frames are analyzed for presence of noise. If noise is detected with high possibility then input frame profile will be used for processing following frames, until new noise frame is detected. \n\n**samples**\n\n    Set size of single frame in number of samples. Allowed range is from 512 to 65536. Default frame size is 8192 samples. \n\n**softness**\n\n    Set softness applied inside thresholding function. Allowed range is from 0 to 10. Default softness is 1. \n\n",
  "filter_type": "af",
  "formula_input_typings": null,
  "formula_output_typings": null,
  "id": "ff_af_afwtdn",
  "input_stream_typings": [
    {
      "name": "default",
      "type": "AVMEDIA_TYPE_AUDIO"
    }
  ],
  "is_input_dynamic": false,
  "is_output_dynamic": false,
  "is_support_timeline": true,
  "name": "afwtdn",
  "options": [
    {
      "alias": [
        "sigma"
      ],
      "choices": [],
      "default": 0.0,
      "description": "<dd><p>Set the noise sigma, allowed range is from 0 to 1.\nDefault value is 0.\nThis option controls strength of denoising applied to input samples.\nMost useful way to set this option is via decibels, eg. -45dB.\n</p>\n</dd>",
      "name": "sigma",
      "required": false,
      "typing": "float"
    },
    {
      "alias": [
        "levels"
      ],
      "choices": [],
      "default": 10,
      "description": "<dd><p>Set the number of wavelet levels of decomposition.\nAllowed range is from 1 to 12.\nDefault value is 10.\nSetting this too low make denoising performance very poor.\n</p>\n</dd>",
      "name": "levels",
      "required": false,
      "typing": "int"
    },
    {
      "alias": [
        "wavet"
      ],
      "choices": [
        {
          "help": "sym2",
          "name": "sym2",
          "value": "SYM2"
        },
        {
          "help": "sym4",
          "name": "sym4",
          "value": "SYM4"
        },
        {
          "help": "rbior68",
          "name": "rbior68",
          "value": "RBIOR68"
        },
        {
          "help": "deb10",
          "name": "deb10",
          "value": "DEB10"
        },
        {
          "help": "sym10",
          "name": "sym10",
          "value": "SYM10"
        },
        {
          "help": "coif5",
          "name": "coif5",
          "value": "COIF5"
        },
        {
          "help": "bl3",
          "name": "bl3",
          "value": "BL3"
        }
      ],
      "default": "SYM10",
      "description": "<dd><p>Set wavelet type for decomposition of input frame.\nThey are sorted by number of coefficients, from lowest to highest.\nMore coefficients means worse filtering speed, but overall better quality.\nAvailable wavelets are:\n</p>\n<dl compact=\"compact\">\n<dt>\u2018<samp>sym2</samp>\u2019</dt>\n<dt>\u2018<samp>sym4</samp>\u2019</dt>\n<dt>\u2018<samp>rbior68</samp>\u2019</dt>\n<dt>\u2018<samp>deb10</samp>\u2019</dt>\n<dt>\u2018<samp>sym10</samp>\u2019</dt>\n<dt>\u2018<samp>coif5</samp>\u2019</dt>\n<dt>\u2018<samp>bl3</samp>\u2019</dt>\n</dl>\n</dd>",
      "name": "wavet",
      "required": false,
      "typing": "int"
    },
    {
      "alias": [
        "percent"
      ],
      "choices": [],
      "default": 85.0,
      "description": "<dd><p>Set percent of full denoising. Allowed range is from 0 to 100 percent.\nDefault value is 85 percent or partial denoising.\n</p>\n</dd>",
      "name": "percent",
      "required": false,
      "typing": "float"
    },
    {
      "alias": [
        "profile"
      ],
      "choices": [],
      "default": 0,
      "description": "<dd><p>If enabled, first input frame will be used as noise profile.\nIf first frame samples contain non-noise performance will be very poor.\n</p>\n</dd>",
      "name": "profile",
      "required": false,
      "typing": "bool"
    },
    {
      "alias": [
        "adaptive"
      ],
      "choices": [],
      "default": 0,
      "description": "<dd><p>If enabled, input frames are analyzed for presence of noise.\nIf noise is detected with high possibility then input frame profile will be\nused for processing following frames, until new noise frame is detected.\n</p>\n</dd>",
      "name": "adaptive",
      "required": false,
      "typing": "bool"
    },
    {
      "alias": [
        "samples"
      ],
      "choices": [],
      "default": 8192,
      "description": "<dd><p>Set size of single frame in number of samples. Allowed range is from 512 to\n65536. Default frame size is 8192 samples.\n</p>\n</dd>",
      "name": "samples",
      "required": false,
      "typing": "int"
    },
    {
      "alias": [
        "softness"
      ],
      "choices": [],
      "default": 1.0,
      "description": "<dd><p>Set softness applied inside thresholding function. Allowed range is from 0 to\n10. Default softness is 1.\n</p></dd>",
      "name": "softness",
      "required": false,
      "typing": "float"
    },
    {
      "alias": [],
      "choices": [],
      "default": null,
      "description": "timeline editing",
      "name": "enable",
      "required": false,
      "typing": "str"
    }
  ],
  "output_stream_typings": [
    {
      "name": "default",
      "type": "AVMEDIA_TYPE_AUDIO"
    }
  ],
  "ref": "https://ffmpeg.org/ffmpeg-filters.html#afwtdn"
}
