{
  "description": "### 18.7 avectorscope\n\nConvert input audio to a video output, representing the audio vector\nscope.\n\n\nThe filter is used to measure the difference between channels of stereo\naudio stream. A monaural signal, consisting of identical left and right\nsignal, results in straight vertical line. Any stereo separation is visible\nas a deviation from this line, creating a Lissajous figure.\nIf the straight (or deviation from it) but horizontal line appears this\nindicates that the left and right channels are out of phase.\n\n\nThe filter accepts the following options:\n\n\n- **`mode, m`**\n  - Set the vectorscope mode.\nAvailable values are:\n\u2018\nlissajous\n\u2019\nLissajous rotated by 45 degrees.\n\u2018\nlissajous_xy\n\u2019\nSame as above but not rotated.\n\u2018\npolar\n\u2019\nShape resembling half of circle.\nDefault value is \u2018\nlissajous\n\u2019.\n- **`size, s`**\n  - Set the video size for the output. For the syntax of this option, check the\n(ffmpeg-utils)\"Video size\" section in the ffmpeg-utils manual\n.\nDefault value is\n400x400\n.\n- **`rate, r`**\n  - Set the output frame rate. Default value is\n25\n.\n- **`rc`**\n- **`gc`**\n- **`bc`**\n- **`ac`**\n  - Specify the red, green, blue and alpha contrast. Default values are\n40\n,\n160\n,\n80\nand\n255\n.\nAllowed range is\n[0, 255]\n.\n- **`rf`**\n- **`gf`**\n- **`bf`**\n- **`af`**\n  - Specify the red, green, blue and alpha fade. Default values are\n15\n,\n10\n,\n5\nand\n5\n.\nAllowed range is\n[0, 255]\n.\n- **`zoom`**\n  - Set the zoom factor. Default value is\n1\n. Allowed range is\n[0, 10]\n.\nValues lower than\n1\nwill auto adjust zoom factor to maximal possible value.\n- **`draw`**\n  - Set the vectorscope drawing mode.\nAvailable values are:\n\u2018\ndot\n\u2019\nDraw dot for each sample.\n\u2018\nline\n\u2019\nDraw line between previous and current sample.\n\u2018\naaline\n\u2019\nDraw anti-aliased line between previous and current sample.\nDefault value is \u2018\ndot\n\u2019.\n- **`scale`**\n  - Specify amplitude scale of audio samples.\nAvailable values are:\n\u2018\nlin\n\u2019\nLinear.\n\u2018\nsqrt\n\u2019\nSquare root.\n\u2018\ncbrt\n\u2019\nCubic root.\n\u2018\nlog\n\u2019\nLogarithmic.\n- **`swap`**\n  - Swap left channel axis with right channel axis.\n- **`mirror`**\n  - Mirror axis.\n\u2018\nnone\n\u2019\nNo mirror.\n\u2018\nx\n\u2019\nMirror only x axis.\n\u2018\ny\n\u2019\nMirror only y axis.\n\u2018\nxy\n\u2019\nMirror both axis.\nSet the vectorscope mode.\n\n\nAvailable values are:\n\n\n- **`\u2018lissajous\u2019`**\n  - Lissajous rotated by 45 degrees.\n- **`\u2018lissajous_xy\u2019`**\n  - Same as above but not rotated.\n- **`\u2018polar\u2019`**\n  - Shape resembling half of circle.\nLissajous rotated by 45 degrees.\n\n\nSame as above but not rotated.\n\n\nShape resembling half of circle.\n\n\nDefault value is \u2018lissajous\u2019.\n\n\nSet the video size for the output. For the syntax of this option, check the\n(ffmpeg-utils)\"Video size\" section in the ffmpeg-utils manual.\nDefault value is 400x400.\n\n\nSet the output frame rate. Default value is 25.\n\n\nSpecify the red, green, blue and alpha contrast. Default values are 40,\n160, 80 and 255.\nAllowed range is [0, 255].\n\n\nSpecify the red, green, blue and alpha fade. Default values are 15,\n10, 5 and 5.\nAllowed range is [0, 255].\n\n\nSet the zoom factor. Default value is 1. Allowed range is [0, 10].\nValues lower than 1 will auto adjust zoom factor to maximal possible value.\n\n\nSet the vectorscope drawing mode.\n\n\nAvailable values are:\n\n\n- **`\u2018dot\u2019`**\n  - Draw dot for each sample.\n- **`\u2018line\u2019`**\n  - Draw line between previous and current sample.\n- **`\u2018aaline\u2019`**\n  - Draw anti-aliased line between previous and current sample.\nDraw dot for each sample.\n\n\nDraw line between previous and current sample.\n\n\nDraw anti-aliased line between previous and current sample.\n\n\nDefault value is \u2018dot\u2019.\n\n\nSpecify amplitude scale of audio samples.\n\n\nAvailable values are:\n\n\n- **`\u2018lin\u2019`**\n  - Linear.\n- **`\u2018sqrt\u2019`**\n  - Square root.\n- **`\u2018cbrt\u2019`**\n  - Cubic root.\n- **`\u2018log\u2019`**\n  - Logarithmic.\nLinear.\n\n\nSquare root.\n\n\nCubic root.\n\n\nLogarithmic.\n\n\nSwap left channel axis with right channel axis.\n\n\nMirror axis.\n\n\n- **`\u2018none\u2019`**\n  - No mirror.\n- **`\u2018x\u2019`**\n  - Mirror only x axis.\n- **`\u2018y\u2019`**\n  - Mirror only y axis.\n- **`\u2018xy\u2019`**\n  - Mirror both axis.\nNo mirror.\n\n\nMirror only x axis.\n\n\nMirror only y axis.\n\n\nMirror both axis.\n\n\n",
  "filter_type": "avf",
  "formula_input_typings": null,
  "formula_output_typings": null,
  "id": "ff_avf_avectorscope",
  "input_stream_typings": [
    {
      "name": "default",
      "type": "AVMEDIA_TYPE_AUDIO"
    }
  ],
  "is_input_dynamic": false,
  "is_output_dynamic": false,
  "name": "avectorscope",
  "options": [
    {
      "alias": [
        "mode",
        "m"
      ],
      "choices": [
        {
          "help": "",
          "name": "lissajous",
          "value": "LISSAJOUS"
        },
        {
          "help": "",
          "name": "lissajous_xy",
          "value": "LISSAJOUS_XY"
        },
        {
          "help": "",
          "name": "polar",
          "value": "POLAR"
        }
      ],
      "default": "LISSAJOUS",
      "description": "<dd><p>Set the vectorscope mode.\n</p>\n<p>Available values are:\n</p><dl compact=\"compact\">\n<dt>\u2018<samp>lissajous</samp>\u2019</dt>\n<dd><p>Lissajous rotated by 45 degrees.\n</p>\n</dd>\n<dt>\u2018<samp>lissajous_xy</samp>\u2019</dt>\n<dd><p>Same as above but not rotated.\n</p>\n</dd>\n<dt>\u2018<samp>polar</samp>\u2019</dt>\n<dd><p>Shape resembling half of circle.\n</p></dd>\n</dl>\n<p>Default value is \u2018<samp>lissajous</samp>\u2019.\n</p>\n</dd>",
      "name": "mode",
      "required": false,
      "typing": "int"
    },
    {
      "alias": [
        "rate",
        "r"
      ],
      "choices": [],
      "default": "25",
      "description": "<dd><p>Set the output frame rate. Default value is <code>25</code>.\n</p>\n</dd>",
      "name": "rate",
      "required": false,
      "typing": "str"
    },
    {
      "alias": [
        "size",
        "s"
      ],
      "choices": [],
      "default": "400x400",
      "description": "<dd><p>Set the video size for the output. For the syntax of this option, check the\n<a href=\"ffmpeg-utils.html#video-size-syntax\">(ffmpeg-utils)\"Video size\" section in the ffmpeg-utils manual</a>.\nDefault value is <code>400x400</code>.\n</p>\n</dd>",
      "name": "size",
      "required": false,
      "typing": "str"
    },
    {
      "alias": [
        "rc"
      ],
      "choices": [],
      "default": 40,
      "description": "<dd><p>Specify the red, green, blue and alpha contrast. Default values are <code>40</code>,\n<code>160</code>, <code>80</code> and <code>255</code>.\nAllowed range is <code>[0, 255]</code>.\n</p>\n</dd>",
      "name": "rc",
      "required": false,
      "typing": "int"
    },
    {
      "alias": [
        "gc"
      ],
      "choices": [],
      "default": 160,
      "description": "<dd><p>Specify the red, green, blue and alpha contrast. Default values are <code>40</code>,\n<code>160</code>, <code>80</code> and <code>255</code>.\nAllowed range is <code>[0, 255]</code>.\n</p>\n</dd>",
      "name": "gc",
      "required": false,
      "typing": "int"
    },
    {
      "alias": [
        "bc"
      ],
      "choices": [],
      "default": 80,
      "description": "<dd><p>Specify the red, green, blue and alpha contrast. Default values are <code>40</code>,\n<code>160</code>, <code>80</code> and <code>255</code>.\nAllowed range is <code>[0, 255]</code>.\n</p>\n</dd>",
      "name": "bc",
      "required": false,
      "typing": "int"
    },
    {
      "alias": [
        "ac"
      ],
      "choices": [],
      "default": 255,
      "description": "<dd><p>Specify the red, green, blue and alpha contrast. Default values are <code>40</code>,\n<code>160</code>, <code>80</code> and <code>255</code>.\nAllowed range is <code>[0, 255]</code>.\n</p>\n</dd>",
      "name": "ac",
      "required": false,
      "typing": "int"
    },
    {
      "alias": [
        "rf"
      ],
      "choices": [],
      "default": 15,
      "description": "<dd><p>Specify the red, green, blue and alpha fade. Default values are <code>15</code>,\n<code>10</code>, <code>5</code> and <code>5</code>.\nAllowed range is <code>[0, 255]</code>.\n</p>\n</dd>",
      "name": "rf",
      "required": false,
      "typing": "int"
    },
    {
      "alias": [
        "gf"
      ],
      "choices": [],
      "default": 10,
      "description": "<dd><p>Specify the red, green, blue and alpha fade. Default values are <code>15</code>,\n<code>10</code>, <code>5</code> and <code>5</code>.\nAllowed range is <code>[0, 255]</code>.\n</p>\n</dd>",
      "name": "gf",
      "required": false,
      "typing": "int"
    },
    {
      "alias": [
        "bf"
      ],
      "choices": [],
      "default": 5,
      "description": "<dd><p>Specify the red, green, blue and alpha fade. Default values are <code>15</code>,\n<code>10</code>, <code>5</code> and <code>5</code>.\nAllowed range is <code>[0, 255]</code>.\n</p>\n</dd>",
      "name": "bf",
      "required": false,
      "typing": "int"
    },
    {
      "alias": [
        "af"
      ],
      "choices": [],
      "default": 5,
      "description": "<dd><p>Specify the red, green, blue and alpha fade. Default values are <code>15</code>,\n<code>10</code>, <code>5</code> and <code>5</code>.\nAllowed range is <code>[0, 255]</code>.\n</p>\n</dd>",
      "name": "af",
      "required": false,
      "typing": "int"
    },
    {
      "alias": [
        "zoom"
      ],
      "choices": [],
      "default": 1.0,
      "description": "<dd><p>Set the zoom factor. Default value is <code>1</code>. Allowed range is <code>[0, 10]</code>.\nValues lower than <var>1</var> will auto adjust zoom factor to maximal possible value.\n</p>\n</dd>",
      "name": "zoom",
      "required": false,
      "typing": "float"
    },
    {
      "alias": [
        "draw"
      ],
      "choices": [
        {
          "help": "draw dots",
          "name": "dot",
          "value": "DOT"
        },
        {
          "help": "draw lines",
          "name": "line",
          "value": "LINE"
        },
        {
          "help": "draw anti-aliased lines",
          "name": "aaline",
          "value": "AALINE"
        }
      ],
      "default": "DOT",
      "description": "<dd><p>Set the vectorscope drawing mode.\n</p>\n<p>Available values are:\n</p><dl compact=\"compact\">\n<dt>\u2018<samp>dot</samp>\u2019</dt>\n<dd><p>Draw dot for each sample.\n</p>\n</dd>\n<dt>\u2018<samp>line</samp>\u2019</dt>\n<dd><p>Draw line between previous and current sample.\n</p>\n</dd>\n<dt>\u2018<samp>aaline</samp>\u2019</dt>\n<dd><p>Draw anti-aliased line between previous and current sample.\n</p></dd>\n</dl>\n<p>Default value is \u2018<samp>dot</samp>\u2019.\n</p>\n</dd>",
      "name": "draw",
      "required": false,
      "typing": "int"
    },
    {
      "alias": [
        "scale"
      ],
      "choices": [
        {
          "help": "linear",
          "name": "lin",
          "value": "LIN"
        },
        {
          "help": "square root",
          "name": "sqrt",
          "value": "SQRT"
        },
        {
          "help": "cube root",
          "name": "cbrt",
          "value": "CBRT"
        },
        {
          "help": "logarithmic",
          "name": "log",
          "value": "LOG"
        }
      ],
      "default": "LIN",
      "description": "<dd><p>Specify amplitude scale of audio samples.\n</p>\n<p>Available values are:\n</p><dl compact=\"compact\">\n<dt>\u2018<samp>lin</samp>\u2019</dt>\n<dd><p>Linear.\n</p>\n</dd>\n<dt>\u2018<samp>sqrt</samp>\u2019</dt>\n<dd><p>Square root.\n</p>\n</dd>\n<dt>\u2018<samp>cbrt</samp>\u2019</dt>\n<dd><p>Cubic root.\n</p>\n</dd>\n<dt>\u2018<samp>log</samp>\u2019</dt>\n<dd><p>Logarithmic.\n</p></dd>\n</dl>\n</dd>",
      "name": "scale",
      "required": false,
      "typing": "int"
    },
    {
      "alias": [
        "swap"
      ],
      "choices": [],
      "default": 1,
      "description": "<dd><p>Swap left channel axis with right channel axis.\n</p>\n</dd>",
      "name": "swap",
      "required": false,
      "typing": "bool"
    },
    {
      "alias": [
        "mirror"
      ],
      "choices": [
        {
          "help": "no mirror",
          "name": "none",
          "value": 0
        },
        {
          "help": "mirror x",
          "name": "x",
          "value": 1
        },
        {
          "help": "mirror y",
          "name": "y",
          "value": 2
        },
        {
          "help": "mirror both",
          "name": "xy",
          "value": 3
        }
      ],
      "default": 0,
      "description": "<dd><p>Mirror axis.\n</p>\n<dl compact=\"compact\">\n<dt>\u2018<samp>none</samp>\u2019</dt>\n<dd><p>No mirror.\n</p>\n</dd>\n<dt>\u2018<samp>x</samp>\u2019</dt>\n<dd><p>Mirror only x axis.\n</p>\n</dd>\n<dt>\u2018<samp>y</samp>\u2019</dt>\n<dd><p>Mirror only y axis.\n</p>\n</dd>\n<dt>\u2018<samp>xy</samp>\u2019</dt>\n<dd><p>Mirror both axis.\n</p></dd>\n</dl>\n</dd>",
      "name": "mirror",
      "required": false,
      "typing": "int"
    }
  ],
  "output_stream_typings": [
    {
      "name": "default",
      "type": "AVMEDIA_TYPE_VIDEO"
    }
  ],
  "ref": "https://ffmpeg.org/ffmpeg-filters.html#avectorscope"
}
