{
  "description": "### 18.10 ebur128\n\nEBU R128 scanner filter. This filter takes an audio stream and analyzes its\nloudness level. By default, it logs a message at a frequency of 10Hz with the\nMomentary loudness (identified by `M`), Short-term loudness (`S`), Integrated\nloudness (`I`) and Loudness Range (`LRA`).\n\nThe filter can only analyze streams which have sample format is double-\nprecision floating point. The input stream will be converted to this\nspecification, if needed. Users may need to insert aformat and/or aresample\nfilters after this filter to obtain the original parameters.\n\nThe filter also has a video output (see the video option) with a real time\ngraph to observe the loudness evolution. The graphic contains the logged\nmessage mentioned above, so it is not printed anymore when this option is set,\nunless the verbose logging is set. The main graphing area contains the short-\nterm loudness (3 seconds of analysis), and the gauge on the right is for the\nmomentary loudness (400 milliseconds), but can optionally be configured to\ninstead display short-term loudness (see gauge).\n\nThe green area marks a +/- 1LU target range around the target loudness\n(-23LUFS by default, unless modified through target).\n\nMore information about the Loudness Recommendation EBU R128 on\n<http://tech.ebu.ch/loudness>.\n\nThe filter accepts the following options:\n\n**video**\n\n    Activate the video output. The audio stream is passed unchanged whether this option is set or no. The video stream will be the first output stream if activated. Default is 0. \n\n**size**\n\n    Set the video size. This option is for video only. For the syntax of this option, check the (ffmpeg-utils)\"Video size\" section in the ffmpeg-utils manual. Default and minimum resolution is 640x480. \n\n**meter**\n\n    Set the EBU scale meter. Default is 9. Common values are 9 and 18, respectively for EBU scale meter +9 and EBU scale meter +18. Any other integer value between this range is allowed. \n\n**metadata**\n\n    Set metadata injection. If set to 1, the audio input will be segmented into 100ms output frames, each of them containing various loudness information in metadata. All the metadata keys are prefixed with lavfi.r128.. Default is 0. \n\n**framelog**\n\n    Force the frame logging level. Available values are: \u2018quiet\u2019 logging disabled \u2018info\u2019 information logging level \u2018verbose\u2019 verbose logging level By default, the logging level is set to info. If the video or the metadata options are set, it switches to verbose. \n\n**peak**\n\n    Set peak mode(s). Available modes can be cumulated (the option is a flag type). Possible values are: \u2018none\u2019 Disable any peak mode (default). \u2018sample\u2019 Enable sample-peak mode. Simple peak mode looking for the higher sample value. It logs a message for sample-peak (identified by SPK). \u2018true\u2019 Enable true-peak mode. If enabled, the peak lookup is done on an over-sampled version of the input stream for better peak accuracy. It logs a message for true-peak. (identified by TPK) and true-peak per frame (identified by FTPK). This mode requires a build with libswresample. \n\n**dualmono**\n\n    Treat mono input files as \"dual mono\". If a mono file is intended for playback on a stereo system, its EBU R128 measurement will be perceptually incorrect. If set to true, this option will compensate for this effect. Multi-channel input files are not affected by this option. \n\n**panlaw**\n\n    Set a specific pan law to be used for the measurement of dual mono files. This parameter is optional, and has a default value of -3.01dB. \n\n**target**\n\n    Set a specific target level (in LUFS) used as relative zero in the visualization. This parameter is optional and has a default value of -23LUFS as specified by EBU R128. However, material published online may prefer a level of -16LUFS (e.g. for use with podcasts or video platforms). \n\n**gauge**\n\n    Set the value displayed by the gauge. Valid values are momentary and s shortterm. By default the momentary value will be used, but in certain scenarios it may be more useful to observe the short term value instead (e.g. live mixing). \n\n**scale**\n\n    Sets the display scale for the loudness. Valid parameters are absolute (in LUFS) or relative (LU) relative to the target. This only affects the video output, not the summary or continuous log output. \n\n**integrated**\n\n    Read-only exported value for measured integrated loudness, in LUFS. \n\n**range**\n\n    Read-only exported value for measured loudness range, in LU. \n\n**lra_low**\n\n    Read-only exported value for measured LRA low, in LUFS. \n\n**lra_high**\n\n    Read-only exported value for measured LRA high, in LUFS. \n\n**sample_peak**\n\n    Read-only exported value for measured sample peak, in dBFS. \n\n**true_peak**\n\n    Read-only exported value for measured true peak, in dBFS. \n\n",
  "filter_type": "af",
  "formula_input_typings": null,
  "formula_output_typings": "[StreamType.video] if video else [] + [StreamType.audio]",
  "id": "ff_af_ebur128",
  "input_stream_typings": [
    {
      "name": "default",
      "type": "AVMEDIA_TYPE_AUDIO"
    }
  ],
  "is_input_dynamic": false,
  "is_output_dynamic": true,
  "name": "ebur128",
  "options": [
    {
      "alias": [
        "video"
      ],
      "choices": [],
      "default": 0,
      "description": "<dd><p>Activate the video output. The audio stream is passed unchanged whether this\noption is set or no. The video stream will be the first output stream if\nactivated. Default is <code>0</code>.\n</p>\n</dd>",
      "name": "video",
      "required": false,
      "typing": "bool"
    },
    {
      "alias": [
        "size"
      ],
      "choices": [],
      "default": "640x480",
      "description": "<dd><p>Set the video size. This option is for video only. For the syntax of this\noption, check the\n<a href=\"ffmpeg-utils.html#video-size-syntax\">(ffmpeg-utils)\"Video size\" section in the ffmpeg-utils manual</a>.\nDefault and minimum resolution is <code>640x480</code>.\n</p>\n</dd>",
      "name": "size",
      "required": false,
      "typing": "str"
    },
    {
      "alias": [
        "meter"
      ],
      "choices": [],
      "default": 9,
      "description": "<dd><p>Set the EBU scale meter. Default is <code>9</code>. Common values are <code>9</code> and\n<code>18</code>, respectively for EBU scale meter +9 and EBU scale meter +18. Any\nother integer value between this range is allowed.\n</p>\n</dd>",
      "name": "meter",
      "required": false,
      "typing": "int"
    },
    {
      "alias": [
        "framelog"
      ],
      "choices": [
        {
          "help": "logging disabled",
          "name": "quiet",
          "value": -8
        },
        {
          "help": "information logging level",
          "name": "info",
          "value": 32
        },
        {
          "help": "verbose logging level",
          "name": "verbose",
          "value": 40
        }
      ],
      "default": -1,
      "description": "<dd><p>Force the frame logging level.\n</p>\n<p>Available values are:\n</p><dl compact=\"compact\">\n<dt>\u2018<samp>quiet</samp>\u2019</dt>\n<dd><p>logging disabled\n</p></dd>\n<dt>\u2018<samp>info</samp>\u2019</dt>\n<dd><p>information logging level\n</p></dd>\n<dt>\u2018<samp>verbose</samp>\u2019</dt>\n<dd><p>verbose logging level\n</p></dd>\n</dl>\n<p>By default, the logging level is set to <var>info</var>. If the <samp>video</samp> or\nthe <samp>metadata</samp> options are set, it switches to <var>verbose</var>.\n</p>\n</dd>",
      "name": "framelog",
      "required": false,
      "typing": "int"
    },
    {
      "alias": [
        "metadata"
      ],
      "choices": [],
      "default": 0,
      "description": "<dd><p>Set metadata injection. If set to <code>1</code>, the audio input will be segmented\ninto 100ms output frames, each of them containing various loudness information\nin metadata.  All the metadata keys are prefixed with <code>lavfi.r128.</code>.\n</p>\n<p>Default is <code>0</code>.\n</p>\n</dd>",
      "name": "metadata",
      "required": false,
      "typing": "bool"
    },
    {
      "alias": [
        "peak"
      ],
      "choices": [
        {
          "help": "disable any peak mode",
          "name": "none",
          "value": "PEAK_MODE_NONE"
        },
        {
          "help": "enable peak-sample mode",
          "name": "sample",
          "value": "PEAK_MODE_SAMPLES_PEAKS"
        },
        {
          "help": "enable true-peak mode",
          "name": "true",
          "value": "PEAK_MODE_TRUE_PEAKS"
        }
      ],
      "default": "PEAK_MODE_NONE",
      "description": "<dd><p>Set peak mode(s).\n</p>\n<p>Available modes can be cumulated (the option is a <code>flag</code> type). Possible\nvalues are:\n</p><dl compact=\"compact\">\n<dt>\u2018<samp>none</samp>\u2019</dt>\n<dd><p>Disable any peak mode (default).\n</p></dd>\n<dt>\u2018<samp>sample</samp>\u2019</dt>\n<dd><p>Enable sample-peak mode.\n</p>\n<p>Simple peak mode looking for the higher sample value. It logs a message\nfor sample-peak (identified by <code>SPK</code>).\n</p></dd>\n<dt>\u2018<samp>true</samp>\u2019</dt>\n<dd><p>Enable true-peak mode.\n</p>\n<p>If enabled, the peak lookup is done on an over-sampled version of the input\nstream for better peak accuracy. It logs a message for true-peak.\n(identified by <code>TPK</code>) and true-peak per frame (identified by <code>FTPK</code>).\nThis mode requires a build with <code>libswresample</code>.\n</p></dd>\n</dl>\n</dd>",
      "name": "peak",
      "required": false,
      "typing": "str"
    },
    {
      "alias": [
        "dualmono"
      ],
      "choices": [],
      "default": 0,
      "description": "<dd><p>Treat mono input files as \"dual mono\". If a mono file is intended for playback\non a stereo system, its EBU R128 measurement will be perceptually incorrect.\nIf set to <code>true</code>, this option will compensate for this effect.\nMulti-channel input files are not affected by this option.\n</p>\n</dd>",
      "name": "dualmono",
      "required": false,
      "typing": "bool"
    },
    {
      "alias": [
        "panlaw"
      ],
      "choices": [],
      "default": -3.01029995663978,
      "description": "<dd><p>Set a specific pan law to be used for the measurement of dual mono files.\nThis parameter is optional, and has a default value of -3.01dB.\n</p>\n</dd>",
      "name": "panlaw",
      "required": false,
      "typing": "float"
    },
    {
      "alias": [
        "target"
      ],
      "choices": [],
      "default": -23,
      "description": "<dd><p>Set a specific target level (in LUFS) used as relative zero in the visualization.\nThis parameter is optional and has a default value of -23LUFS as specified\nby EBU R128. However, material published online may prefer a level of -16LUFS\n(e.g. for use with podcasts or video platforms).\n</p>\n</dd>",
      "name": "target",
      "required": false,
      "typing": "int"
    },
    {
      "alias": [
        "gauge"
      ],
      "choices": [
        {
          "help": "display momentary value",
          "name": "momentary",
          "value": "GAUGE_TYPE_MOMENTARY"
        },
        {
          "help": "display momentary value",
          "name": "m",
          "value": "GAUGE_TYPE_MOMENTARY"
        },
        {
          "help": "display short-term value",
          "name": "shortterm",
          "value": "GAUGE_TYPE_SHORTTERM"
        },
        {
          "help": "display short-term value",
          "name": "s",
          "value": "GAUGE_TYPE_SHORTTERM"
        }
      ],
      "default": 0,
      "description": "<dd><p>Set the value displayed by the gauge. Valid values are <code>momentary</code> and s\n<code>shortterm</code>. By default the momentary value will be used, but in certain\nscenarios it may be more useful to observe the short term value instead (e.g.\nlive mixing).\n</p>\n</dd>",
      "name": "gauge",
      "required": false,
      "typing": "int"
    },
    {
      "alias": [
        "scale"
      ],
      "choices": [
        {
          "help": "display absolute values (LUFS)",
          "name": "absolute",
          "value": "SCALE_TYPE_ABSOLUTE"
        },
        {
          "help": "display absolute values (LUFS)",
          "name": "LUFS",
          "value": "SCALE_TYPE_ABSOLUTE"
        },
        {
          "help": "display values relative to target (LU)",
          "name": "relative",
          "value": "SCALE_TYPE_RELATIVE"
        },
        {
          "help": "display values relative to target (LU)",
          "name": "LU",
          "value": "SCALE_TYPE_RELATIVE"
        }
      ],
      "default": 0,
      "description": "<dd><p>Sets the display scale for the loudness. Valid parameters are <code>absolute</code>\n(in LUFS) or <code>relative</code> (LU) relative to the target. This only affects the\nvideo output, not the summary or continuous log output.\n</p>\n</dd>",
      "name": "scale",
      "required": false,
      "typing": "int"
    },
    {
      "alias": [
        "integrated"
      ],
      "choices": [],
      "default": 0.0,
      "description": "<dd><p>Read-only exported value for measured integrated loudness, in LUFS.\n</p>\n</dd>",
      "name": "integrated",
      "required": false,
      "typing": "float"
    },
    {
      "alias": [
        "range"
      ],
      "choices": [],
      "default": 0.0,
      "description": "<dd><p>Read-only exported value for measured loudness range, in LU.\n</p>\n</dd>",
      "name": "range",
      "required": false,
      "typing": "float"
    },
    {
      "alias": [
        "lra_low"
      ],
      "choices": [],
      "default": 0.0,
      "description": "<dd><p>Read-only exported value for measured LRA low, in LUFS.\n</p>\n</dd>",
      "name": "lra_low",
      "required": false,
      "typing": "float"
    },
    {
      "alias": [
        "lra_high"
      ],
      "choices": [],
      "default": 0.0,
      "description": "<dd><p>Read-only exported value for measured LRA high, in LUFS.\n</p>\n</dd>",
      "name": "lra_high",
      "required": false,
      "typing": "float"
    },
    {
      "alias": [
        "sample_peak"
      ],
      "choices": [],
      "default": 0.0,
      "description": "<dd><p>Read-only exported value for measured sample peak, in dBFS.\n</p>\n</dd>",
      "name": "sample_peak",
      "required": false,
      "typing": "float"
    },
    {
      "alias": [
        "true_peak"
      ],
      "choices": [],
      "default": 0.0,
      "description": "<dd><p>Read-only exported value for measured true peak, in dBFS.\n</p></dd>",
      "name": "true_peak",
      "required": false,
      "typing": "float"
    }
  ],
  "output_stream_typings": [],
  "ref": "https://ffmpeg.org/ffmpeg-filters.html#ebur128"
}
