{
  "description": "### 16.10 allrgb, allyuv, color, colorchart, colorspectrum, haldclutsrc,\nnullsrc, pal75bars, pal100bars, rgbtestsrc, smptebars, smptehdbars, testsrc,\ntestsrc2, yuvtestsrc\n\nThe `allrgb` source returns frames of size 4096x4096 of all rgb colors.\n\nThe `allyuv` source returns frames of size 4096x4096 of all yuv colors.\n\nThe `color` source provides an uniformly colored input.\n\nThe `colorchart` source provides a colors checker chart.\n\nThe `colorspectrum` source provides a color spectrum input.\n\nThe `haldclutsrc` source provides an identity Hald CLUT. See also haldclut\nfilter.\n\nThe `nullsrc` source returns unprocessed video frames. It is mainly useful to\nbe employed in analysis / debugging tools, or as the source for filters which\nignore the input data.\n\nThe `pal75bars` source generates a color bars pattern, based on EBU PAL\nrecommendations with 75% color levels.\n\nThe `pal100bars` source generates a color bars pattern, based on EBU PAL\nrecommendations with 100% color levels.\n\nThe `rgbtestsrc` source generates an RGB test pattern useful for detecting RGB\nvs BGR issues. You should see a red, green and blue stripe from top to bottom.\n\nThe `smptebars` source generates a color bars pattern, based on the SMPTE\nEngineering Guideline EG 1-1990.\n\nThe `smptehdbars` source generates a color bars pattern, based on the SMPTE RP\n219-2002.\n\nThe `testsrc` source generates a test video pattern, showing a color pattern,\na scrolling gradient and a timestamp. This is mainly intended for testing\npurposes.\n\nThe `testsrc2` source is similar to testsrc, but supports more pixel formats\ninstead of just `rgb24`. This allows using it as an input for other tests\nwithout requiring a format conversion.\n\nThe `yuvtestsrc` source generates an YUV test pattern. You should see a y, cb\nand cr stripe from top to bottom.\n\nThe sources accept the following parameters:\n\n**level**\n\n    Specify the level of the Hald CLUT, only available in the haldclutsrc source. A level of N generates a picture of N*N*N by N*N*N pixels to be used as identity matrix for 3D lookup tables. Each component is coded on a 1/(N*N) scale. \n\n**color, c**\n\n    Specify the color of the source, only available in the color source. For the syntax of this option, check the (ffmpeg-utils)\"Color\" section in the ffmpeg-utils manual. \n\n**size, s**\n\n    Specify the size of the sourced video. For the syntax of this option, check the (ffmpeg-utils)\"Video size\" section in the ffmpeg-utils manual. The default value is 320x240. This option is not available with the allrgb, allyuv, and haldclutsrc filters. \n\n**rate, r**\n\n    Specify the frame rate of the sourced video, as the number of frames generated per second. It has to be a string in the format frame_rate_num/frame_rate_den, an integer number, a floating point number or a valid video frame rate abbreviation. The default value is \"25\". \n\n**duration, d**\n\n    Set the duration of the sourced video. See (ffmpeg-utils)the Time duration section in the ffmpeg-utils(1) manual for the accepted syntax. If not specified, or the expressed duration is negative, the video is supposed to be generated forever. Since the frame rate is used as time base, all frames including the last one will have their full duration. If the specified duration is not a multiple of the frame duration, it will be rounded up. \n\n**sar**\n\n    Set the sample aspect ratio of the sourced video. \n\n**alpha**\n\n    Specify the alpha (opacity) of the background, only available in the testsrc2 source. The value must be between 0 (fully transparent) and 255 (fully opaque, the default). \n\n**decimals, n**\n\n    Set the number of decimals to show in the timestamp, only available in the testsrc source. The displayed timestamp value will correspond to the original timestamp value multiplied by the power of 10 of the specified value. Default value is 0. \n\n**type**\n\n    Set the type of the color spectrum, only available in the colorspectrum source. Can be one of the following: \u2018black\u2019 \u2018white\u2019 \u2018all\u2019 \n\n**patch_size**\n\n    Set patch size of single color patch, only available in the colorchart source. Default is 64x64. \n\n**preset**\n\n    Set colorchecker colors preset, only available in the colorchart source. Available values are: \u2018reference\u2019 \u2018skintones\u2019 Default value is reference. \n\n",
  "filter_type": "vsrc",
  "formula_input_typings": null,
  "formula_output_typings": null,
  "id": "ff_vsrc_colorchart",
  "input_stream_typings": [],
  "is_input_dynamic": false,
  "is_output_dynamic": false,
  "is_support_framesync": false,
  "is_support_timeline": false,
  "name": "colorchart",
  "options": [
    {
      "alias": [
        "rate",
        "r"
      ],
      "choices": [],
      "default": "25",
      "description": "<dd><p>Specify the frame rate of the sourced video, as the number of frames\ngenerated per second. It has to be a string in the format\n<var>frame_rate_num</var>/<var>frame_rate_den</var>, an integer number, a floating point\nnumber or a valid video frame rate abbreviation. The default value is\n\"25\".\n</p>\n</dd>",
      "name": "rate",
      "required": false,
      "typing": "str"
    },
    {
      "alias": [
        "duration",
        "d"
      ],
      "choices": [],
      "default": -1,
      "description": "<dd><p>Set the duration of the sourced video. See\n<a href=\"ffmpeg-utils.html#time-duration-syntax\">(ffmpeg-utils)the Time duration section in the ffmpeg-utils(1) manual</a>\nfor the accepted syntax.\n</p>\n<p>If not specified, or the expressed duration is negative, the video is\nsupposed to be generated forever.\n</p>\n<p>Since the frame rate is used as time base, all frames including the last one\nwill have their full duration. If the specified duration is not a multiple\nof the frame duration, it will be rounded up.\n</p>\n</dd>",
      "name": "duration",
      "required": false,
      "typing": "int"
    },
    {
      "alias": [
        "sar"
      ],
      "choices": [],
      "default": 1.0,
      "description": "<dd><p>Set the sample aspect ratio of the sourced video.\n</p>\n</dd>",
      "name": "sar",
      "required": false,
      "typing": "float"
    },
    {
      "alias": [
        "patch_size"
      ],
      "choices": [],
      "default": "64x64",
      "description": "<dd><p>Set patch size of single color patch, only available in the\n<code>colorchart</code> source. Default is <code>64x64</code>.\n</p>\n</dd>",
      "name": "patch_size",
      "required": false,
      "typing": "str"
    },
    {
      "alias": [
        "preset"
      ],
      "choices": [
        {
          "help": "reference",
          "name": "reference",
          "value": 0
        },
        {
          "help": "skintones",
          "name": "skintones",
          "value": 1
        }
      ],
      "default": 0,
      "description": "<dd><p>Set colorchecker colors preset, only available in the\n<code>colorchart</code> source.\n</p>\n<p>Available values are:\n</p><dl compact=\"compact\">\n<dt>\u2018<samp>reference</samp>\u2019</dt>\n<dt>\u2018<samp>skintones</samp>\u2019</dt>\n</dl>\n<p>Default value is <code>reference</code>.\n</p></dd>",
      "name": "preset",
      "required": false,
      "typing": "int"
    }
  ],
  "output_stream_typings": [
    {
      "name": "default",
      "type": "AVMEDIA_TYPE_VIDEO"
    }
  ],
  "ref": "https://ffmpeg.org/ffmpeg-filters.html#allrgb_002c-allyuv_002c-color_002c-colorchart_002c-colorspectrum_002c-haldclutsrc_002c-nullsrc_002c-pal75bars_002c-pal100bars_002c-rgbtestsrc_002c-smptebars_002c-smptehdbars_002c-testsrc_002c-testsrc2_002c-yuvtestsrc"
}
