{
  "description": "### 11.252 thistogram\n\nCompute and draw a color distribution histogram for the input video across time.\n\n\nUnlike histogram video filter which only shows histogram of single input frame\nat certain time, this filter shows also past histograms of number of frames defined\nby width option.\n\n\nThe computed histogram is a representation of the color component\ndistribution in an image.\n\n\nThe filter accepts the following options:\n\n\n- **`width, w`**\n  - Set width of single color component output. Default value is\n0\n.\nValue of\n0\nmeans width will be picked from input video.\nThis also set number of passed histograms to keep.\nAllowed range is [0, 8192].\n- **`display_mode, d`**\n  - Set display mode.\nIt accepts the following values:\n\u2018\nstack\n\u2019\nPer color component graphs are placed below each other.\n\u2018\nparade\n\u2019\nPer color component graphs are placed side by side.\n\u2018\noverlay\n\u2019\nPresents information identical to that in the\nparade\n, except\nthat the graphs representing color components are superimposed directly\nover one another.\nDefault is\nstack\n.\n- **`levels_mode, m`**\n  - Set mode. Can be either\nlinear\n, or\nlogarithmic\n.\nDefault is\nlinear\n.\n- **`components, c`**\n  - Set what color components to display.\nDefault is\n7\n.\n- **`bgopacity, b`**\n  - Set background opacity. Default is\n0.9\n.\n- **`envelope, e`**\n  - Show envelope. Default is disabled.\n- **`ecolor, ec`**\n  - Set envelope color. Default is\ngold\n.\n- **`slide`**\n  - Set slide mode.\nAvailable values for slide is:\n\u2018\nframe\n\u2019\nDraw new frame when right border is reached.\n\u2018\nreplace\n\u2019\nReplace old columns with new ones.\n\u2018\nscroll\n\u2019\nScroll from right to left.\n\u2018\nrscroll\n\u2019\nScroll from left to right.\n\u2018\npicture\n\u2019\nDraw single picture.\nDefault is\nreplace\n.\nSet width of single color component output. Default value is 0.\nValue of 0 means width will be picked from input video.\nThis also set number of passed histograms to keep.\nAllowed range is [0, 8192].\n\n\nSet display mode.\nIt accepts the following values:\n\n\n- **`\u2018stack\u2019`**\n  - Per color component graphs are placed below each other.\n- **`\u2018parade\u2019`**\n  - Per color component graphs are placed side by side.\n- **`\u2018overlay\u2019`**\n  - Presents information identical to that in the\nparade\n, except\nthat the graphs representing color components are superimposed directly\nover one another.\nPer color component graphs are placed below each other.\n\n\nPer color component graphs are placed side by side.\n\n\nPresents information identical to that in the parade, except\nthat the graphs representing color components are superimposed directly\nover one another.\n\n\nDefault is stack.\n\n\nSet mode. Can be either linear, or logarithmic.\nDefault is linear.\n\n\nSet what color components to display.\nDefault is 7.\n\n\nSet background opacity. Default is 0.9.\n\n\nShow envelope. Default is disabled.\n\n\nSet envelope color. Default is gold.\n\n\nSet slide mode.\n\n\nAvailable values for slide is:\n\n\n- **`\u2018frame\u2019`**\n  - Draw new frame when right border is reached.\n- **`\u2018replace\u2019`**\n  - Replace old columns with new ones.\n- **`\u2018scroll\u2019`**\n  - Scroll from right to left.\n- **`\u2018rscroll\u2019`**\n  - Scroll from left to right.\n- **`\u2018picture\u2019`**\n  - Draw single picture.\nDraw new frame when right border is reached.\n\n\nReplace old columns with new ones.\n\n\nScroll from right to left.\n\n\nScroll from left to right.\n\n\nDraw single picture.\n\n\nDefault is replace.\n\n\n",
  "filter_type": "vf",
  "formula_input_typings": null,
  "formula_output_typings": null,
  "id": "ff_vf_thistogram",
  "input_stream_typings": [
    {
      "name": "default",
      "type": "AVMEDIA_TYPE_VIDEO"
    }
  ],
  "is_input_dynamic": false,
  "is_output_dynamic": false,
  "name": "thistogram",
  "options": [
    {
      "alias": [
        "width",
        "w"
      ],
      "choices": [],
      "default": 0,
      "description": "<dd><p>Set width of single color component output. Default value is <code>0</code>.\nValue of <code>0</code> means width will be picked from input video.\nThis also set number of passed histograms to keep.\nAllowed range is [0, 8192].\n</p>\n</dd>",
      "name": "width",
      "required": false,
      "typing": "int"
    },
    {
      "alias": [
        "display_mode",
        "d"
      ],
      "choices": [
        {
          "help": "((void*)0)",
          "name": "overlay",
          "value": 0
        },
        {
          "help": "((void*)0)",
          "name": "parade",
          "value": 1
        },
        {
          "help": "((void*)0)",
          "name": "stack",
          "value": 2
        }
      ],
      "default": 2,
      "description": "<dd><p>Set display mode.\nIt accepts the following values:\n</p><dl compact=\"compact\">\n<dt>\u2018<samp>stack</samp>\u2019</dt>\n<dd><p>Per color component graphs are placed below each other.\n</p>\n</dd>\n<dt>\u2018<samp>parade</samp>\u2019</dt>\n<dd><p>Per color component graphs are placed side by side.\n</p>\n</dd>\n<dt>\u2018<samp>overlay</samp>\u2019</dt>\n<dd><p>Presents information identical to that in the <code>parade</code>, except\nthat the graphs representing color components are superimposed directly\nover one another.\n</p></dd>\n</dl>\n<p>Default is <code>stack</code>.\n</p>\n</dd>",
      "name": "display_mode",
      "required": false,
      "typing": "int"
    },
    {
      "alias": [
        "levels_mode",
        "m"
      ],
      "choices": [
        {
          "help": "((void*)0)",
          "name": "linear",
          "value": 0
        },
        {
          "help": "((void*)0)",
          "name": "logarithmic",
          "value": 1
        }
      ],
      "default": 0,
      "description": "<dd><p>Set mode. Can be either <code>linear</code>, or <code>logarithmic</code>.\nDefault is <code>linear</code>.\n</p>\n</dd>",
      "name": "levels_mode",
      "required": false,
      "typing": "int"
    },
    {
      "alias": [
        "components",
        "c"
      ],
      "choices": [],
      "default": 7,
      "description": "<dd><p>Set what color components to display.\nDefault is <code>7</code>.\n</p>\n</dd>",
      "name": "components",
      "required": false,
      "typing": "int"
    },
    {
      "alias": [
        "bgopacity",
        "b"
      ],
      "choices": [],
      "default": 0.9,
      "description": "<dd><p>Set background opacity. Default is <code>0.9</code>.\n</p>\n</dd>",
      "name": "bgopacity",
      "required": false,
      "typing": "float"
    },
    {
      "alias": [
        "envelope",
        "e"
      ],
      "choices": [],
      "default": 0,
      "description": "<dd><p>Show envelope. Default is disabled.\n</p>\n</dd>",
      "name": "envelope",
      "required": false,
      "typing": "bool"
    },
    {
      "alias": [
        "ecolor",
        "ec"
      ],
      "choices": [],
      "default": "gold",
      "description": "<dd><p>Set envelope color. Default is <code>gold</code>.\n</p>\n</dd>",
      "name": "ecolor",
      "required": false,
      "typing": "str"
    },
    {
      "alias": [
        "slide"
      ],
      "choices": [
        {
          "help": "draw new frames",
          "name": "frame",
          "value": 0
        },
        {
          "help": "replace old columns with new",
          "name": "replace",
          "value": 1
        },
        {
          "help": "scroll from right to left",
          "name": "scroll",
          "value": 2
        },
        {
          "help": "scroll from left to right",
          "name": "rscroll",
          "value": 3
        },
        {
          "help": "display graph in single frame",
          "name": "picture",
          "value": 4
        }
      ],
      "default": 1,
      "description": "<dd><p>Set slide mode.\n</p>\n<p>Available values for slide is:\n</p><dl compact=\"compact\">\n<dt>\u2018<samp>frame</samp>\u2019</dt>\n<dd><p>Draw new frame when right border is reached.\n</p>\n</dd>\n<dt>\u2018<samp>replace</samp>\u2019</dt>\n<dd><p>Replace old columns with new ones.\n</p>\n</dd>\n<dt>\u2018<samp>scroll</samp>\u2019</dt>\n<dd><p>Scroll from right to left.\n</p>\n</dd>\n<dt>\u2018<samp>rscroll</samp>\u2019</dt>\n<dd><p>Scroll from left to right.\n</p>\n</dd>\n<dt>\u2018<samp>picture</samp>\u2019</dt>\n<dd><p>Draw single picture.\n</p></dd>\n</dl>\n<p>Default is <code>replace</code>.\n</p></dd>",
      "name": "slide",
      "required": false,
      "typing": "int"
    }
  ],
  "output_stream_typings": [
    {
      "name": "default",
      "type": "AVMEDIA_TYPE_VIDEO"
    }
  ],
  "ref": "https://ffmpeg.org/ffmpeg-filters.html#thistogram"
}
